<?xml version="1.0" encoding="utf-8" ?><dwsync><file name="dashboard_sales.js" server="designannexe.com/thesameheart.com/" local="3435640430" remote="80747384268" /><file name="dashboard_sales.min.js" server="designannexe.com/thesameheart.com/" local="3435640430" remote="97927253452" /><file name="editor_plugin.js" server="designannexe.com/thesameheart.com/" local="3435640430" remote="72157449676" /><file name="jquery.flot.js" server="designannexe.com/thesameheart.com/" local="3435640430" remote="63567515144" /><file name="jquery.flot.min.js" server="designannexe.com/thesameheart.com/" local="3435640430" remote="80747384328" /><file name="jquery.flot.resize.js" server="designannexe.com/thesameheart.com/" local="3435640430" remote="93632286216" /><file name="jquery.flot.resize.min.js" server="designannexe.com/thesameheart.com/" local="3435640430" remote="110812155400" /><file name="product-ordering.js" server="designannexe.com/thesameheart.com/" local="3435640430" remote="85042351624" /><file name="quick-edit.js" server="designannexe.com/thesameheart.com/" local="3435640430" remote="59272547848" /><file name="term-ordering.js" server="designannexe.com/thesameheart.com/" local="3435640430" remote="72157449736" /><file name="ui-datepicker.js" server="designannexe.com/thesameheart.com/" local="3435640430" remote="72157449736" /><file name="woocommerce_admin.js" server="designannexe.com/thesameheart.com/" local="3435640430" remote="89337318920" /><file name="woocommerce_admin.min.js" server="designannexe.com/thesameheart.com/" local="3435640430" remote="106517188104" /><file name="write-panels.js" server="designannexe.com/thesameheart.com/" local="3435640430" remote="67862482440" /><file name="write-panels.min.js" server="designannexe.com/thesameheart.com/" local="3435640430" remote="85042351624" /></dwsync>